setup.py
aws_ops.egg-info/PKG-INFO
aws_ops.egg-info/SOURCES.txt
aws_ops.egg-info/dependency_links.txt
aws_ops.egg-info/entry_points.txt
aws_ops.egg-info/requires.txt
aws_ops.egg-info/top_level.txt
cloudcaster/__init__.py
cloudcaster/cloudcaster.py
cloudcaster/json2yaml.py
ec2autoimage/__init__.py
ec2autoimage/ec2autoimage.py
ec2cleanami/__init__.py
ec2cleanami/ec2cleanami.py
ec2cleanlc/__init__.py
ec2cleanlc/ec2cleanlc.py
ec2createapp/__init__.py
ec2createapp/ec2createapp.py
ec2nodefind/__init__.py
ec2nodefind/ec2nodefind.py
ec2rotatehosts/__init__.py
ec2rotatehosts/ec2rotatehosts.py