Metadata-Version: 1.0
Name: aws-ops
Version: 0.0.2
Summary: Building special snowflakes consistently
Home-page: https://github.com/WrathOfChris/ops
Author: Chris Maxwell
Author-email: foo@bar.com
License: BSD 2-Clause
Platform: UNKNOWN
